[
    {
        "date": "2023-06-19T00:00:00.000Z",
        "lecturer": "Мартинюк В.П., 022 IV н.к.,",
        "subject": "Інформаційно-аналітичне забезпечення економічної безпеки",
        "number": 3,
        "urls": [
            "https://meet.google.com/jhy-vefn-oeh"
        ]
    },
    {
        "date": "2023-06-22T00:00:00.000Z",
        "lecturer": "Білик О.І., 003 V н.к.,",
        "subject": "Страховий менеджмент",
        "number": 3,
        "urls": []
    },
    {
        "date": "2023-06-26T00:00:00.000Z",
        "lecturer": "Карковська В.Я., 022 IV н.к.,",
        "subject": "Комплексне забезпечення фінансово-економічної безпеки",
        "number": 3,
        "urls": [
            "https://us04web.zoom.us/j/72441672423?pwd=ufLONUVxwzzzBSd9BMUZbDt1vletRh.1"
        ]
    },
    {
        "date": "2023-06-29T00:00:00.000Z",
        "lecturer": "Сокіл О.Г., 022 IV н.к.,",
        "subject": "Обліково-аналітичне забезпечення економічної безпеки на підприємстві",
        "number": 3,
        "urls": [
            "https://us04web.zoom.us/j/78143265654?pwd=U3wga9j1GfOxfub01Gkut1y3EtpwkB.1"
        ]
    }
]