[
    {
        "subject": "Технології і матеріали у графічному дизайні",
        "lecturer": "ДС-23, 216 Гол. н.к., ",
        "location": " практична",
        "urls": [],
        "type": "practical",
        "isFirstWeek": true,
        "isSecondWeek": true,
        "isFirstSubgroup": true,
        "isSecondSubgroup": true,
        "day": 1,
        "number": 3
    },
    {
        "subject": "Декоративно-ужиткове мистецтво",
        "lecturer": "ДС-34, ",
        "location": " лабораторна",
        "urls": [
            "https://teams.microsoft.com/l/meetup-join/19%3a14xqarfqxt8gXnwRVLuQNDRY9IESDsL4PNT2ADS88Iw1%40thread.tacv2/1677087292609?context=%7b%22Tid%22%3a%227631cd62-5187-4e15-8b8e-ef653e366e7a%22%2c%22Oid%22%3a%22260ff81a-034f-4c31-8188-b24108b40c81%22%7d"
        ],
        "type": "lab",
        "isFirstWeek": false,
        "isSecondWeek": true,
        "isFirstSubgroup": true,
        "isSecondSubgroup": true,
        "day": 1,
        "number": 4
    },
    {
        "subject": "Декоративно-ужиткове мистецтво",
        "lecturer": "ДС-32, ",
        "location": " лабораторна",
        "urls": [
            "https://teams.microsoft.com/l/meetup-join/19%3aG1cJ8_zbIzi6_lRA98XXsWPB9bpHjdVpl1M45HI8ds01%40thread.tacv2/1677086860663?context=%7b%22Tid%22%3a%227631cd62-5187-4e15-8b8e-ef653e366e7a%22%2c%22Oid%22%3a%22260ff81a-034f-4c31-8188-b24108b40c81%22%7d"
        ],
        "type": "lab",
        "isFirstWeek": true,
        "isSecondWeek": false,
        "isFirstSubgroup": true,
        "isSecondSubgroup": true,
        "day": 1,
        "number": 5
    },
    {
        "subject": "Композиція та формотворення у дизайні, частина 2",
        "lecturer": "ДС-15, 105б Гол. н.к., ",
        "location": " практична",
        "urls": [],
        "type": "practical",
        "isFirstWeek": true,
        "isSecondWeek": true,
        "isFirstSubgroup": true,
        "isSecondSubgroup": true,
        "day": 2,
        "number": 1
    },
    {
        "subject": "Композиція та формотворення у дизайні, частина 2",
        "lecturer": "ДС-15, 105б Гол. н.к., ",
        "location": " практична",
        "urls": [],
        "type": "practical",
        "isFirstWeek": true,
        "isSecondWeek": true,
        "isFirstSubgroup": true,
        "isSecondSubgroup": true,
        "day": 2,
        "number": 2
    },
    {
        "subject": "Декоративно-ужиткове мистецтво",
        "lecturer": "ДС-31, ",
        "location": " лабораторна",
        "urls": [
            "https://teams.microsoft.com/l/meetup-join/19%3autY-Bh7mefhZKCxpugqtjurzWrJ8-vAuwKfMAZlVdBY1%40thread.tacv2/1677087473163?context=%7b%22Tid%22%3a%227631cd62-5187-4e15-8b8e-ef653e366e7a%22%2c%22Oid%22%3a%22260ff81a-034f-4c31-8188-b24108b40c81%22%7d"
        ],
        "type": "lab",
        "isFirstWeek": true,
        "isSecondWeek": false,
        "isFirstSubgroup": true,
        "isSecondSubgroup": true,
        "day": 3,
        "number": 2
    },
    {
        "subject": "Декоративно-ужиткове мистецтво",
        "lecturer": "ДС-33, ",
        "location": " практична",
        "urls": [
            "https://teams.microsoft.com/l/meetup-join/19%3aX6msIlce5IaMJ0P_AGW5vDjSyp-e3lUf-iV6-CHFeS81%40thread.tacv2/1677087613454?context=%7b%22Tid%22%3a%227631cd62-5187-4e15-8b8e-ef653e366e7a%22%2c%22Oid%22%3a%22260ff81a-034f-4c31-8188-b24108b40c81%22%7d"
        ],
        "type": "practical",
        "isFirstWeek": false,
        "isSecondWeek": true,
        "isFirstSubgroup": true,
        "isSecondSubgroup": true,
        "day": 3,
        "number": 2
    },
    {
        "subject": "Технології і матеріали у графічному дизайні",
        "lecturer": "ДС-23, 216 Гол. н.к., ",
        "location": " практична",
        "urls": [],
        "type": "practical",
        "isFirstWeek": true,
        "isSecondWeek": true,
        "isFirstSubgroup": true,
        "isSecondSubgroup": true,
        "day": 3,
        "number": 3
    },
    {
        "subject": "Технології і матеріали у графічному дизайні",
        "lecturer": "ДС-24, 216 Гол. н.к., ",
        "location": " практична",
        "urls": [],
        "type": "practical",
        "isFirstWeek": false,
        "isSecondWeek": true,
        "isFirstSubgroup": true,
        "isSecondSubgroup": true,
        "day": 3,
        "number": 4
    },
    {
        "subject": "Технології і матеріали у графічному дизайні",
        "lecturer": "ДС-23, 216 Гол. н.к., ",
        "location": " практична",
        "urls": [],
        "type": "practical",
        "isFirstWeek": true,
        "isSecondWeek": false,
        "isFirstSubgroup": true,
        "isSecondSubgroup": true,
        "day": 3,
        "number": 4
    },
    {
        "subject": "Технології і матеріали у графічному дизайні",
        "lecturer": "ДС-24, 216 Гол. н.к., ",
        "location": " практична",
        "urls": [],
        "type": "practical",
        "isFirstWeek": true,
        "isSecondWeek": true,
        "isFirstSubgroup": true,
        "isSecondSubgroup": true,
        "day": 3,
        "number": 5
    },
    {
        "subject": "Живопис, рисунок, скульптура, частина 2",
        "lecturer": "АР-17, 322 Гол. н.к., ",
        "location": " лабораторна",
        "urls": [],
        "type": "lab",
        "isFirstWeek": true,
        "isSecondWeek": true,
        "isFirstSubgroup": true,
        "isSecondSubgroup": true,
        "day": 5,
        "number": 3
    },
    {
        "subject": "Живопис, рисунок, скульптура, частина 2",
        "lecturer": "АР-17, 013 III н.к., ",
        "location": " лабораторна",
        "urls": [],
        "type": "lab",
        "isFirstWeek": true,
        "isSecondWeek": true,
        "isFirstSubgroup": true,
        "isSecondSubgroup": true,
        "day": 5,
        "number": 4
    }
]