[
    {
        "subject": "Випусковий редактор на радіо і телебаченні",
        "lecturer": "ЖРЗВ-11, 108 XX н.к., ",
        "location": " практична",
        "urls": [
            "https://us05web.zoom.us/j/82905368250?pwd=aW9yWWlxTjVselFTczZBR25LQ3Qvdz09"
        ],
        "type": "practical",
        "isFirstWeek": false,
        "isSecondWeek": true,
        "isFirstSubgroup": true,
        "isSecondSubgroup": true,
        "day": 3,
        "number": 1
    },
    {
        "subject": "Випусковий редактор на радіо і телебаченні",
        "lecturer": "ЖРЗВ-11, ",
        "location": " лекція",
        "urls": [
            "https://us05web.zoom.us/j/82905368250?pwd=aW9yWWlxTjVselFTczZBR25LQ3Qvdz09"
        ],
        "type": "lection",
        "isFirstWeek": true,
        "isSecondWeek": false,
        "isFirstSubgroup": true,
        "isSecondSubgroup": true,
        "day": 3,
        "number": 1
    }
]