[
    {
        "subject": "Інформатика",
        "lecturer": "ФР-21, 504 XXVIII н.к., ",
        "location": " лабораторна",
        "urls": [],
        "type": "lab",
        "isFirstWeek": true,
        "isSecondWeek": true,
        "isFirstSubgroup": true,
        "isSecondSubgroup": true,
        "day": 1,
        "number": 3
    },
    {
        "subject": "Інформатика та сучасні інформаційні технології",
        "lecturer": "МВ-12, 507 XXVIII н.к., ",
        "location": " лабораторна",
        "urls": [],
        "type": "lab",
        "isFirstWeek": true,
        "isSecondWeek": true,
        "isFirstSubgroup": false,
        "isSecondSubgroup": true,
        "day": 2,
        "number": 1
    },
    {
        "subject": "Інформатика та сучасні інформаційні технології",
        "lecturer": "МВ-13, 507 XXVIII н.к., ",
        "location": " лабораторна",
        "urls": [],
        "type": "lab",
        "isFirstWeek": true,
        "isSecondWeek": true,
        "isFirstSubgroup": false,
        "isSecondSubgroup": true,
        "day": 2,
        "number": 2
    },
    {
        "subject": "Інформатика та сучасні інформаційні технології",
        "lecturer": "МВ-11, 507 XXVIII н.к., ",
        "location": " лабораторна",
        "urls": [],
        "type": "lab",
        "isFirstWeek": true,
        "isSecondWeek": true,
        "isFirstSubgroup": false,
        "isSecondSubgroup": true,
        "day": 2,
        "number": 3
    },
    {
        "subject": "Інформатика та сучасні інформаційні технології",
        "lecturer": "МВ-14, 507 XXVIII н.к., ",
        "location": " лабораторна",
        "urls": [],
        "type": "lab",
        "isFirstWeek": true,
        "isSecondWeek": true,
        "isFirstSubgroup": false,
        "isSecondSubgroup": true,
        "day": 2,
        "number": 4
    }
]