[
    {
        "subject": "Психопедагогіка управління",
        "lecturer": "ПК-41, ",
        "location": " лекція",
        "urls": [],
        "type": "lection",
        "isFirstWeek": true,
        "isSecondWeek": true,
        "isFirstSubgroup": true,
        "isSecondSubgroup": true,
        "day": 3,
        "number": 2
    },
    {
        "subject": "Психопедагогіка управління",
        "lecturer": "ПК-41, ",
        "location": " практична",
        "urls": [],
        "type": "practical",
        "isFirstWeek": true,
        "isSecondWeek": true,
        "isFirstSubgroup": true,
        "isSecondSubgroup": true,
        "day": 3,
        "number": 3
    },
    {
        "subject": "Психопедагогіка управління",
        "lecturer": "ПК-41, ",
        "location": " практична",
        "urls": [],
        "type": "practical",
        "isFirstWeek": true,
        "isSecondWeek": true,
        "isFirstSubgroup": true,
        "isSecondSubgroup": true,
        "day": 3,
        "number": 4
    },
    {
        "subject": "Теорія і методика виховної роботи",
        "lecturer": "ПЦ-21, 701 XXXVI н.к., ",
        "location": " практична",
        "urls": [],
        "type": "practical",
        "isFirstWeek": true,
        "isSecondWeek": true,
        "isFirstSubgroup": true,
        "isSecondSubgroup": true,
        "day": 5,
        "number": 1
    },
    {
        "subject": "Теорія і методика виховної роботи",
        "lecturer": "ПЦ-21, ПЦ-22, 709 XXXVI н.к., ",
        "location": " лекція",
        "urls": [],
        "type": "lection",
        "isFirstWeek": true,
        "isSecondWeek": true,
        "isFirstSubgroup": true,
        "isSecondSubgroup": true,
        "day": 5,
        "number": 2
    },
    {
        "subject": "Теорія і методика виховної роботи",
        "lecturer": "ПЦ-22, 701 XXXVI н.к., ",
        "location": " практична",
        "urls": [],
        "type": "practical",
        "isFirstWeek": false,
        "isSecondWeek": true,
        "isFirstSubgroup": true,
        "isSecondSubgroup": true,
        "day": 5,
        "number": 3
    },
    {
        "subject": "Теорія і методика виховної роботи",
        "lecturer": "ПЦ-21, 701 XXXVI н.к., ",
        "location": " практична",
        "urls": [],
        "type": "practical",
        "isFirstWeek": true,
        "isSecondWeek": false,
        "isFirstSubgroup": true,
        "isSecondSubgroup": true,
        "day": 5,
        "number": 3
    },
    {
        "subject": "Теорія і методика виховної роботи",
        "lecturer": "ПЦ-22, 701 XXXVI н.к., ",
        "location": " практична",
        "urls": [],
        "type": "practical",
        "isFirstWeek": true,
        "isSecondWeek": true,
        "isFirstSubgroup": true,
        "isSecondSubgroup": true,
        "day": 5,
        "number": 4
    }
]