[
    {
        "subject": "\nЗовнішня політика країн Західної Європи",
        "lecturer": " Тишкун Ю.Я., 209 Гол. н.к., Лекція ",
        "location": " \n\n\n\n",
        "urls": [],
        "type": "lection",
        "isFirstWeek": true,
        "isSecondWeek": true,
        "isFirstSubgroup": true,
        "isSecondSubgroup": true,
        "day": 1,
        "number": 4
    },
    {
        "subject": "\nЗовнішня політика країн Західної Європи",
        "lecturer": " Лукач Н.М., 510 II н.к., Практична ",
        "location": " \n\n\n\n\n",
        "urls": [],
        "type": "lection",
        "isFirstWeek": false,
        "isSecondWeek": true,
        "isFirstSubgroup": true,
        "isSecondSubgroup": true,
        "day": 1,
        "number": 5
    },
    {
        "subject": "\nЗовнішня політика країн Західної Європи",
        "lecturer": " Лукач Н.М., 510 II н.к., Практична ",
        "location": " \n\n\n\n",
        "urls": [],
        "type": "lection",
        "isFirstWeek": true,
        "isSecondWeek": true,
        "isFirstSubgroup": true,
        "isSecondSubgroup": true,
        "day": 1,
        "number": 6
    },
    {
        "subject": "\nЗовнішня політика Росії та країн СНД",
        "lecturer": " Кукарцев О.В., 210 Гол. н.к., Практична ",
        "location": " \n\n\n\n",
        "urls": [],
        "type": "lection",
        "isFirstWeek": true,
        "isSecondWeek": true,
        "isFirstSubgroup": true,
        "isSecondSubgroup": true,
        "day": 2,
        "number": 4
    },
    {
        "subject": "\nІноземна мова II, частина 3",
        "lecturer": " Весна М.П., Практична ",
        "location": " \n\n\n\n",
        "urls": [],
        "type": "lection",
        "isFirstWeek": true,
        "isSecondWeek": true,
        "isFirstSubgroup": true,
        "isSecondSubgroup": false,
        "day": 2,
        "number": 5
    },
    {
        "subject": "\nІноземна мова II, частина 3",
        "lecturer": " Нанівський Р.С., Практична ",
        "location": " \n\n\n\n\n",
        "urls": [],
        "type": "lection",
        "isFirstWeek": true,
        "isSecondWeek": true,
        "isFirstSubgroup": false,
        "isSecondSubgroup": true,
        "day": 2,
        "number": 5
    },
    {
        "subject": "\nЗовнішня політика країн Азії та Африки, Північної та Латинської Америки",
        "lecturer": " Рослонь Д., 407 II н.к., Лекція ",
        "location": " \n\n\n\n",
        "urls": [],
        "type": "lection",
        "isFirstWeek": true,
        "isSecondWeek": true,
        "isFirstSubgroup": true,
        "isSecondSubgroup": true,
        "day": 2,
        "number": 6
    },
    {
        "subject": "\nЗовнішня політика Росії та країн СНД",
        "lecturer": " Кукарцев О.В., 407 II н.к., Лекція ",
        "location": " \n\n\n\n",
        "urls": [],
        "type": "lection",
        "isFirstWeek": true,
        "isSecondWeek": true,
        "isFirstSubgroup": true,
        "isSecondSubgroup": true,
        "day": 3,
        "number": 5
    },
    {
        "subject": "\nІноземна мова II, частина 3",
        "lecturer": " Весна М.П., Практична ",
        "location": " \n\n\n\n",
        "urls": [],
        "type": "lection",
        "isFirstWeek": true,
        "isSecondWeek": false,
        "isFirstSubgroup": true,
        "isSecondSubgroup": false,
        "day": 3,
        "number": 6
    },
    {
        "subject": "\nІноземна мова II, частина 3",
        "lecturer": " Бабкіна М.І., Практична ",
        "location": " \n\n\n\n\n",
        "urls": [],
        "type": "lection",
        "isFirstWeek": false,
        "isSecondWeek": true,
        "isFirstSubgroup": true,
        "isSecondSubgroup": true,
        "day": 4,
        "number": 3
    },
    {
        "subject": "\nІноземна мова II, частина 3",
        "lecturer": " Бабкіна М.І., Практична ",
        "location": " \n\n\n\n",
        "urls": [],
        "type": "lection",
        "isFirstWeek": true,
        "isSecondWeek": true,
        "isFirstSubgroup": true,
        "isSecondSubgroup": true,
        "day": 4,
        "number": 4
    },
    {
        "subject": "\nЗовнішня політика країн Західної Європи",
        "lecturer": " Тишкун Ю.Я., 407 II н.к., Лекція ",
        "location": " \n\n\n\n",
        "urls": [],
        "type": "lection",
        "isFirstWeek": true,
        "isSecondWeek": false,
        "isFirstSubgroup": true,
        "isSecondSubgroup": true,
        "day": 4,
        "number": 5
    },
    {
        "subject": "\nПереклад дипломатичних документів та кореспонденції, частина 1",
        "lecturer": " Марціхів Х.Р., Практична ",
        "location": " \n\n\n\n",
        "urls": [],
        "type": "lection",
        "isFirstWeek": false,
        "isSecondWeek": true,
        "isFirstSubgroup": true,
        "isSecondSubgroup": false,
        "day": 4,
        "number": 5
    },
    {
        "subject": "\nПереклад дипломатичних переговорів, конференцій та зустрічей, частина 1",
        "lecturer": " Столярчук Л.Б., Практична ",
        "location": " \n\n\n\n\n",
        "urls": [],
        "type": "lection",
        "isFirstWeek": false,
        "isSecondWeek": true,
        "isFirstSubgroup": false,
        "isSecondSubgroup": true,
        "day": 4,
        "number": 5
    },
    {
        "subject": "\nЗовнішня політика країн Азії та Африки, Північної та Латинської Америки",
        "lecturer": " Кокош А.Д., 309 V н.к., Практична ",
        "location": " \n\n\n\n",
        "urls": [],
        "type": "lection",
        "isFirstWeek": true,
        "isSecondWeek": true,
        "isFirstSubgroup": true,
        "isSecondSubgroup": true,
        "day": 4,
        "number": 6
    },
    {
        "subject": "\nІноземна мова II, частина 3",
        "lecturer": " Нанівський Р.С., Практична ",
        "location": " \n\n\n\n\n",
        "urls": [],
        "type": "lection",
        "isFirstWeek": false,
        "isSecondWeek": true,
        "isFirstSubgroup": false,
        "isSecondSubgroup": true,
        "day": 5,
        "number": 3
    },
    {
        "subject": "\nЗовнішня політика країн Азії та Африки, Північної та Латинської Америки",
        "lecturer": " Кокош А.Д., 313 IV н.к., Практична ",
        "location": " \n\n\n\n\n",
        "urls": [],
        "type": "lection",
        "isFirstWeek": false,
        "isSecondWeek": true,
        "isFirstSubgroup": true,
        "isSecondSubgroup": true,
        "day": 5,
        "number": 4
    },
    {
        "subject": "\nПереклад дипломатичних документів та кореспонденції, частина 1",
        "lecturer": " Марціхів Х.Р., Практична ",
        "location": " \n\n\n\n",
        "urls": [],
        "type": "lection",
        "isFirstWeek": true,
        "isSecondWeek": false,
        "isFirstSubgroup": true,
        "isSecondSubgroup": false,
        "day": 5,
        "number": 4
    },
    {
        "subject": "\nПереклад дипломатичних переговорів, конференцій та зустрічей, частина 1",
        "lecturer": " Столярчук Л.Б., Практична ",
        "location": " \n\n\n\n\n",
        "urls": [],
        "type": "lection",
        "isFirstWeek": true,
        "isSecondWeek": false,
        "isFirstSubgroup": false,
        "isSecondSubgroup": true,
        "day": 5,
        "number": 4
    },
    {
        "subject": "\nПереклад дипломатичних документів та кореспонденції, частина 1",
        "lecturer": " Марціхів Х.Р., Практична ",
        "location": " \n\n\n\n",
        "urls": [],
        "type": "lection",
        "isFirstWeek": true,
        "isSecondWeek": true,
        "isFirstSubgroup": true,
        "isSecondSubgroup": false,
        "day": 5,
        "number": 5
    },
    {
        "subject": "\nПереклад дипломатичних переговорів, конференцій та зустрічей, частина 1",
        "lecturer": " Столярчук Л.Б., Практична ",
        "location": " \n\n\n\n\n",
        "urls": [],
        "type": "lection",
        "isFirstWeek": true,
        "isSecondWeek": true,
        "isFirstSubgroup": false,
        "isSecondSubgroup": true,
        "day": 5,
        "number": 5
    }
]