[
    {
        "subject": "\nМоделювання динаміки бізнес-процесів",
        "lecturer": " Мірошник Р.О.",
        "location": " 515 IV н.к.",
        "urls": [],
        "type": "practical",
        "isFirstWeek": false,
        "isSecondWeek": true,
        "isFirstSubgroup": true,
        "isSecondSubgroup": true,
        "day": 1,
        "number": 4
    },
    {
        "subject": "\nУправління якістю",
        "lecturer": " Грибик І.І.",
        "location": " 515 IV н.к.",
        "urls": [],
        "type": "practical",
        "isFirstWeek": true,
        "isSecondWeek": false,
        "isFirstSubgroup": true,
        "isSecondSubgroup": true,
        "day": 1,
        "number": 4
    },
    {
        "subject": "\nДілова іноземна мова",
        "lecturer": " Жорняк Н.Є.",
        "location": " 044 VII н.к.",
        "urls": [],
        "type": "practical",
        "isFirstWeek": true,
        "isSecondWeek": true,
        "isFirstSubgroup": true,
        "isSecondSubgroup": true,
        "day": 1,
        "number": 5
    },
    {
        "subject": "\nДілова іноземна мова",
        "lecturer": " Жорняк Н.Є.",
        "location": " 044 VII н.к.",
        "urls": [],
        "type": "practical",
        "isFirstWeek": true,
        "isSecondWeek": false,
        "isFirstSubgroup": true,
        "isSecondSubgroup": true,
        "day": 1,
        "number": 6
    },
    {
        "subject": "\nСистемно-управлінська оцінка фінансово-господарської діяльності організації",
        "lecturer": " Гавран В.Я.",
        "location": " 420 IV н.к.",
        "urls": [],
        "type": "practical",
        "isFirstWeek": false,
        "isSecondWeek": true,
        "isFirstSubgroup": true,
        "isSecondSubgroup": true,
        "day": 2,
        "number": 5
    },
    {
        "subject": "\nПрийняття управлінських рішень",
        "lecturer": " Мірошник Р.О.",
        "location": " 425 IV н.к.",
        "urls": [],
        "type": "practical",
        "isFirstWeek": true,
        "isSecondWeek": true,
        "isFirstSubgroup": true,
        "isSecondSubgroup": true,
        "day": 2,
        "number": 6
    },
    {
        "subject": "\nМоделювання динаміки бізнес-процесів",
        "lecturer": " Матвій І.Є.",
        "location": " 514 IV н.к.",
        "urls": [],
        "type": "lection",
        "isFirstWeek": true,
        "isSecondWeek": false,
        "isFirstSubgroup": true,
        "isSecondSubgroup": true,
        "day": 3,
        "number": 2
    },
    {
        "subject": "\nСтратегічне управління підприємством",
        "lecturer": " Карий О.І.",
        "location": " 417 IV н.к.",
        "urls": [],
        "type": "lection",
        "isFirstWeek": true,
        "isSecondWeek": true,
        "isFirstSubgroup": true,
        "isSecondSubgroup": true,
        "day": 3,
        "number": 3
    },
    {
        "subject": "\nСистемно-управлінська оцінка фінансово-господарської діяльності організації",
        "lecturer": " Гавран В.Я.",
        "location": " 417 IV н.к.",
        "urls": [],
        "type": "lection",
        "isFirstWeek": true,
        "isSecondWeek": false,
        "isFirstSubgroup": true,
        "isSecondSubgroup": true,
        "day": 3,
        "number": 4
    },
    {
        "subject": "\nУправління якістю",
        "lecturer": " Грибик І.І.",
        "location": " 417 IV н.к.",
        "urls": [],
        "type": "lection",
        "isFirstWeek": false,
        "isSecondWeek": true,
        "isFirstSubgroup": true,
        "isSecondSubgroup": true,
        "day": 3,
        "number": 4
    },
    {
        "subject": "\nПрийняття управлінських рішень",
        "lecturer": " Мірошник Р.О.",
        "location": " 420 IV н.к.",
        "urls": [],
        "type": "lection",
        "isFirstWeek": true,
        "isSecondWeek": false,
        "isFirstSubgroup": true,
        "isSecondSubgroup": true,
        "day": 4,
        "number": 5
    },
    {
        "subject": "\nСтратегічне управління підприємством",
        "lecturer": " Когут М.В.",
        "location": " 515 IV н.к.",
        "urls": [],
        "type": "practical",
        "isFirstWeek": true,
        "isSecondWeek": true,
        "isFirstSubgroup": true,
        "isSecondSubgroup": true,
        "day": 4,
        "number": 6
    },
    {
        "subject": "\nМоделювання динаміки бізнес-процесів",
        "lecturer": " Матвій І.Є.",
        "location": " 427(1) IV н.к.",
        "urls": [],
        "type": "lab",
        "isFirstWeek": true,
        "isSecondWeek": true,
        "isFirstSubgroup": true,
        "isSecondSubgroup": true,
        "day": 4,
        "number": 7
    },
    {
        "subject": "\nСистемно-управлінська оцінка фінансово-господарської діяльності організації",
        "lecturer": " Дзюбіна А.В.",
        "location": " 515 IV н.к.",
        "urls": [],
        "type": "lab",
        "isFirstWeek": true,
        "isSecondWeek": true,
        "isFirstSubgroup": true,
        "isSecondSubgroup": true,
        "day": 5,
        "number": 5
    },
    {
        "subject": "\nУправління якістю",
        "lecturer": " Смолінська Н.В.",
        "location": " 427(1) IV н.к.",
        "urls": [],
        "type": "lab",
        "isFirstWeek": true,
        "isSecondWeek": true,
        "isFirstSubgroup": true,
        "isSecondSubgroup": true,
        "day": 5,
        "number": 6
    }
]